payplug/__init__.py
payplug/__version__.py
payplug/config.py
payplug/exceptions.py
payplug/network.py
payplug/notifications.py
payplug/resources.py
payplug/routes.py
payplug/certs/cacert.pem
payplug-1.4.0.dist-info/LICENCE.md
payplug-1.4.0.dist-info/METADATA
payplug-1.4.0.dist-info/WHEEL
payplug-1.4.0.dist-info/top_level.txt
payplug-1.4.0.dist-info/RECORD
