Metadata-Version: 2.1
Name: payplug
Version: 1.4.0
Summary: PayPlug payment solution
Home-page: https://github.com/payplug/payplug-python/releases
Author: PayPlug
Author-email: support@payplug.com
License: UNKNOWN
Keywords: payplug payment integration api
Platform: UNKNOWN
Classifier: Development Status :: 5 - Production/Stable
Classifier: Intended Audience :: Developers
Classifier: Topic :: Software Development :: Libraries :: Python Modules
Classifier: Operating System :: OS Independent
Classifier: License :: OSI Approved :: MIT License
Classifier: Programming Language :: Python :: 2
Classifier: Programming Language :: Python :: 2.6
Classifier: Programming Language :: Python :: 2.7
Classifier: Programming Language :: Python :: 3
Classifier: Programming Language :: Python :: 3.1
Classifier: Programming Language :: Python :: 3.2
Classifier: Programming Language :: Python :: 3.3
Classifier: Programming Language :: Python :: 3.4
Classifier: Programming Language :: Python :: 3.5
Classifier: Programming Language :: Python :: Implementation :: PyPy
Requires-Dist: requests (<3.0,>=1.0.1)
Requires-Dist: six (>=1.4.0)
Requires-Dist: pyOpenSSL (>=0.15)
